{
  "_doc": [
    "Hand-curated anchor set for the map-search calibration check.",
    "",
    "`bots` is a stylistically-diverse roster intended to span the ability",
    "range. `pairs` is a list of [winner, loser] dominance claims that",
    "should hold on ANY reasonable map — these are bots that consistently",
    "live near the top tier vs. consistently live near the bottom tier in",
    "every saved league we have. A map that fails too many of these is",
    "unlikely to be measuring 'good bot' the way we mean it.",
    "",
    "Not a total order. Pairs are restricted to obvious cases — strong",
    "vs. weak — so the calibration check has near-zero false positives.",
    "Mid-tier bots (Aggressive, Spearhead, SlowAndSteady) are deliberately",
    "absent from `pairs` because their order is map-dependent."
  ],
  "bots": [
    "Trinity",
    "Membrane",
    "Conductor",
    "Crusader",
    "Bulwark",
    "SlowAndSteady",
    "Aggressive",
    "Spearhead",
    "Repel",
    "Random",
    "Pacifist_01",
    "Pacifist_03"
  ],
  "pairs": [
    ["Trinity", "Random"],
    ["Trinity", "Pacifist_01"],
    ["Trinity", "Pacifist_03"],
    ["Trinity", "Repel"],
    ["Membrane", "Random"],
    ["Membrane", "Pacifist_01"],
    ["Membrane", "Repel"],
    ["Conductor", "Random"],
    ["Conductor", "Pacifist_01"],
    ["Conductor", "Repel"],
    ["Crusader", "Random"],
    ["Crusader", "Pacifist_01"],
    ["Crusader", "Repel"],
    ["Bulwark", "Random"],
    ["Bulwark", "Pacifist_01"],
    ["Bulwark", "Repel"]
  ],
  "altBots": [
    "Trinity",
    "Conqueror",
    "Lance",
    "TideWall",
    "Stalker",
    "Citadel",
    "SlowAndSteady",
    "Bully",
    "Repel",
    "Random",
    "Pacifist_02",
    "Pacifist_04"
  ],
  "altPairs": [
    ["Trinity", "Random"],
    ["Trinity", "Pacifist_02"],
    ["Trinity", "Repel"],
    ["Conqueror", "Random"],
    ["Conqueror", "Pacifist_04"],
    ["Lance", "Random"],
    ["Lance", "Pacifist_02"],
    ["TideWall", "Random"],
    ["TideWall", "Repel"],
    ["Stalker", "Random"],
    ["Stalker", "Pacifist_04"],
    ["Citadel", "Random"]
  ]
}
